spartera_cli/__init__.py
spartera_cli/client.py
spartera_cli/main.py
spartera_cli/commands/__init__.py
spartera_cli/commands/asset.py
spartera_cli/commands/auth.py
spartera_cli/commands/base.py
spartera_cli/commands/connection.py
spartera_cli/commands/process.py
spartera_cli/commands/stats.py
spartera_cli/commands/user.py
spartera_cli/utils/__init__.py
spartera_cli/utils/auth.py
spartera_cli/utils/config.py
spartera_cli/utils/formatting.py
spartera_cli-1.0.0.dist-info/METADATA
spartera_cli-1.0.0.dist-info/WHEEL
spartera_cli-1.0.0.dist-info/entry_points.txt
spartera_cli-1.0.0.dist-info/licenses/LICENSE
spartera_cli-1.0.0.dist-info/RECORD
